{
  "updatedAt": "2026-07-16T03:11:33+08:00",
  "matches": {
    "can-mar": {
      "title": "加拿大 vs 摩洛哥",
      "kickoff": "2026-07-05T01:00:00+08:00",
      "lastScoreCheck": "2026-07-16T03:11:33+08:00",
      "espnStatus": "FT",
      "espnState": "post",
      "completed": true,
      "scoreDisplay": "CAN 0 MAR 3",
      "espnOdds": {},
      "status": "finished",
      "lastOddsUpdate": "2026-07-05T02:55:45+08:00",
      "lastPrematchOddsUpdate": "2026-07-05T01:00:46+08:00",
      "clock": "",
      "liveEvents": [
        {
          "time": "20'",
          "team": "MAR",
          "type": "黃牌",
          "rawType": "Yellow Card",
          "player": "Redouane Halhal",
          "scoringPlay": false,
          "yellowCard": true,
          "redCard": false,
          "penaltyKick": false,
          "ownGoal": false,
          "shootout": false
        },
        {
          "time": "40'",
          "team": "MAR",
          "type": "黃牌",
          "rawType": "Yellow Card",
          "player": "Achraf Hakimi",
          "scoringPlay": false,
          "yellowCard": true,
          "redCard": false,
          "penaltyKick": false,
          "ownGoal": false,
          "shootout": false
        },
        {
          "time": "40'",
          "team": "CAN",
          "type": "黃牌",
          "rawType": "Yellow Card",
          "player": "Richie Laryea",
          "scoringPlay": false,
          "yellowCard": true,
          "redCard": false,
          "penaltyKick": false,
          "ownGoal": false,
          "shootout": false
        },
        {
          "time": "43'",
          "team": "CAN",
          "type": "黃牌",
          "rawType": "Yellow Card",
          "player": "Jonathan David",
          "scoringPlay": false,
          "yellowCard": true,
          "redCard": false,
          "penaltyKick": false,
          "ownGoal": false,
          "shootout": false
        },
        {
          "time": "45'",
          "team": "MAR",
          "type": "黃牌",
          "rawType": "Yellow Card",
          "player": "Azzedine Ounahi",
          "scoringPlay": false,
          "yellowCard": true,
          "redCard": false,
          "penaltyKick": false,
          "ownGoal": false,
          "shootout": false
        },
        {
          "time": "45'+6'",
          "team": "MAR",
          "type": "黃牌",
          "rawType": "Yellow Card",
          "player": "Bilal El Khannouss",
          "scoringPlay": false,
          "yellowCard": true,
          "redCard": false,
          "penaltyKick": false,
          "ownGoal": false,
          "shootout": false
        },
        {
          "time": "49'",
          "team": "CAN",
          "type": "黃牌",
          "rawType": "Yellow Card",
          "player": "Luc de Fougerolles",
          "scoringPlay": false,
          "yellowCard": true,
          "redCard": false,
          "penaltyKick": false,
          "ownGoal": false,
          "shootout": false
        },
        {
          "time": "50'",
          "team": "MAR",
          "type": "進球",
          "rawType": "Goal",
          "player": "Azzedine Ounahi",
          "scoringPlay": true,
          "yellowCard": false,
          "redCard": false,
          "penaltyKick": false,
          "ownGoal": false,
          "shootout": false
        },
        {
          "time": "67'",
          "team": "CAN",
          "type": "黃牌",
          "rawType": "Yellow Card",
          "player": "Cyle Larin",
          "scoringPlay": false,
          "yellowCard": true,
          "redCard": false,
          "penaltyKick": false,
          "ownGoal": false,
          "shootout": false
        },
        {
          "time": "82'",
          "team": "MAR",
          "type": "進球",
          "rawType": "Goal",
          "player": "Azzedine Ounahi",
          "scoringPlay": true,
          "yellowCard": false,
          "redCard": false,
          "penaltyKick": false,
          "ownGoal": false,
          "shootout": false
        },
        {
          "time": "90'+8'",
          "team": "MAR",
          "type": "進球",
          "rawType": "Goal",
          "player": "Soufiane Rahimi",
          "scoringPlay": true,
          "yellowCard": false,
          "redCard": false,
          "penaltyKick": false,
          "ownGoal": false,
          "shootout": false
        }
      ],
      "liveStats": {
        "teams": [
          "CAN",
          "MAR"
        ],
        "rows": [
          {
            "name": "totalShots",
            "label": "射門",
            "values": {
              "CAN": "10",
              "MAR": "5"
            }
          },
          {
            "name": "shotsOnTarget",
            "label": "射正",
            "values": {
              "CAN": "3",
              "MAR": "4"
            }
          },
          {
            "name": "possessionPct",
            "label": "控球",
            "values": {
              "CAN": "44.7%",
              "MAR": "55.3%"
            }
          },
          {
            "name": "foulsCommitted",
            "label": "犯規",
            "values": {
              "CAN": "24",
              "MAR": "14"
            }
          },
          {
            "name": "yellowCards",
            "label": "黃牌",
            "values": {
              "CAN": "4",
              "MAR": "4"
            }
          },
          {
            "name": "redCards",
            "label": "紅牌",
            "values": {
              "CAN": "0",
              "MAR": "0"
            }
          },
          {
            "name": "wonCorners",
            "label": "角球",
            "values": {
              "CAN": "11",
              "MAR": "1"
            }
          },
          {
            "name": "offsides",
            "label": "越位",
            "values": {
              "CAN": "2",
              "MAR": "3"
            }
          },
          {
            "name": "saves",
            "label": "撲救",
            "values": {
              "CAN": "1",
              "MAR": "3"
            }
          }
        ],
        "sourceError": null
      },
      "cardCounts": {
        "CAN": {
          "yellow": 4,
          "red": 0
        },
        "MAR": {
          "yellow": 4,
          "red": 0
        }
      },
      "liveDataUpdatedAt": "2026-07-16T03:11:33+08:00",
      "taiwanSportsLottery": {
        "source": "Taiwan Sports Lottery",
        "status": "missing",
        "url": "https://www.sportslottery.com.tw/sportsbook/world-cup",
        "dataUrl": "https://blob3rd.sportslottery.com.tw/apidata/Pre/WC-Games.en.json",
        "updatedAt": "2026-07-05T03:00:44+08:00",
        "error": "World Cup public JSON did not include this match."
      },
      "lastLiveOddsUpdate": "2026-07-05T02:55:45+08:00",
      "winner": "MAR",
      "resultSummary": "完賽 CAN 0 MAR 3，勝方/晉級方：MAR。總進球 3，大 2.5、小 3.5，BTTS No。90 分鐘勝負與讓球若涉及延長/PK，仍需以 Binance 結算規則核對。",
      "finishedAt": "2026-07-05T03:06:12+08:00"
    },
    "par-fra": {
      "title": "巴拉圭 vs 法國",
      "kickoff": "2026-07-05T05:00:00+08:00",
      "lastScoreCheck": "2026-07-16T03:11:33+08:00",
      "espnStatus": "FT",
      "espnState": "post",
      "completed": true,
      "scoreDisplay": "PAR 0 FRA 1",
      "espnOdds": {},
      "status": "finished",
      "lastOddsUpdate": "2026-07-05T06:56:02+08:00",
      "lastPrematchOddsUpdate": "2026-07-05T05:00:47+08:00",
      "clock": "",
      "liveEvents": [
        {
          "time": "19'",
          "team": "FRA",
          "type": "黃牌",
          "rawType": "Yellow Card",
          "player": "Bradley Barcola",
          "scoringPlay": false,
          "yellowCard": true,
          "redCard": false,
          "penaltyKick": false,
          "ownGoal": false,
          "shootout": false
        },
        {
          "time": "70'",
          "team": "FRA",
          "type": "點球進球",
          "rawType": "Penalty - Scored",
          "player": "Kylian Mbappé",
          "scoringPlay": true,
          "yellowCard": false,
          "redCard": false,
          "penaltyKick": true,
          "ownGoal": false,
          "shootout": false
        },
        {
          "time": "81'",
          "team": "FRA",
          "type": "黃牌",
          "rawType": "Yellow Card",
          "player": "Manu Koné",
          "scoringPlay": false,
          "yellowCard": true,
          "redCard": false,
          "penaltyKick": false,
          "ownGoal": false,
          "shootout": false
        },
        {
          "time": "90'+7'",
          "team": "FRA",
          "type": "黃牌",
          "rawType": "Yellow Card",
          "player": "Michael Olise",
          "scoringPlay": false,
          "yellowCard": true,
          "redCard": false,
          "penaltyKick": false,
          "ownGoal": false,
          "shootout": false
        }
      ],
      "liveStats": {
        "teams": [
          "PAR",
          "FRA"
        ],
        "rows": [
          {
            "name": "totalShots",
            "label": "射門",
            "values": {
              "PAR": "5",
              "FRA": "15"
            }
          },
          {
            "name": "shotsOnTarget",
            "label": "射正",
            "values": {
              "PAR": "1",
              "FRA": "5"
            }
          },
          {
            "name": "possessionPct",
            "label": "控球",
            "values": {
              "PAR": "24.1%",
              "FRA": "75.9%"
            }
          },
          {
            "name": "foulsCommitted",
            "label": "犯規",
            "values": {
              "PAR": "13",
              "FRA": "11"
            }
          },
          {
            "name": "yellowCards",
            "label": "黃牌",
            "values": {
              "PAR": "0",
              "FRA": "3"
            }
          },
          {
            "name": "redCards",
            "label": "紅牌",
            "values": {
              "PAR": "0",
              "FRA": "0"
            }
          },
          {
            "name": "wonCorners",
            "label": "角球",
            "values": {
              "PAR": "2",
              "FRA": "12"
            }
          },
          {
            "name": "offsides",
            "label": "越位",
            "values": {
              "PAR": "0",
              "FRA": "0"
            }
          },
          {
            "name": "saves",
            "label": "撲救",
            "values": {
              "PAR": "4",
              "FRA": "1"
            }
          }
        ],
        "sourceError": null
      },
      "cardCounts": {
        "PAR": {
          "yellow": 0,
          "red": 0
        },
        "FRA": {
          "yellow": 3,
          "red": 0
        }
      },
      "liveDataUpdatedAt": "2026-07-16T03:11:33+08:00",
      "taiwanSportsLottery": {
        "source": "Taiwan Sports Lottery",
        "status": "missing",
        "url": "https://www.sportslottery.com.tw/sportsbook/world-cup",
        "dataUrl": "https://blob3rd.sportslottery.com.tw/apidata/Pre/WC-Games.en.json",
        "updatedAt": "2026-07-05T07:00:59+08:00",
        "error": "World Cup public JSON did not include this match."
      },
      "lastLiveOddsUpdate": "2026-07-05T06:56:02+08:00",
      "winner": "FRA",
      "resultSummary": "完賽 PAR 0 FRA 1，勝方/晉級方：FRA。總進球 1，小 2.5、小 3.5，BTTS No。90 分鐘勝負與讓球若涉及延長/PK，仍需以 Binance 結算規則核對。",
      "finishedAt": "2026-07-05T07:06:59+08:00"
    },
    "bra-nor": {
      "title": "巴西 vs 挪威",
      "kickoff": "2026-07-06T04:00:00+08:00",
      "lastScoreCheck": "2026-07-16T03:11:33+08:00",
      "espnStatus": "FT",
      "espnState": "post",
      "completed": true,
      "scoreDisplay": "BRA 1 NOR 2",
      "espnOdds": {},
      "status": "finished",
      "lastOddsUpdate": "2026-07-06T00:09:53+08:00",
      "lastPrematchOddsUpdate": "2026-07-06T00:09:53+08:00",
      "clock": "",
      "liveEvents": [
        {
          "time": "79'",
          "team": "NOR",
          "type": "進球",
          "rawType": "Goal - Header",
          "player": "Erling Haaland",
          "scoringPlay": true,
          "yellowCard": false,
          "redCard": false,
          "penaltyKick": false,
          "ownGoal": false,
          "shootout": false
        },
        {
          "time": "90'",
          "team": "NOR",
          "type": "進球",
          "rawType": "Goal",
          "player": "Erling Haaland",
          "scoringPlay": true,
          "yellowCard": false,
          "redCard": false,
          "penaltyKick": false,
          "ownGoal": false,
          "shootout": false
        },
        {
          "time": "90'+6'",
          "team": "BRA",
          "type": "黃牌",
          "rawType": "Yellow Card",
          "player": "Neymar",
          "scoringPlay": false,
          "yellowCard": true,
          "redCard": false,
          "penaltyKick": false,
          "ownGoal": false,
          "shootout": false
        },
        {
          "time": "90'+10'",
          "team": "BRA",
          "type": "點球進球",
          "rawType": "Penalty - Scored",
          "player": "Neymar",
          "scoringPlay": true,
          "yellowCard": false,
          "redCard": false,
          "penaltyKick": true,
          "ownGoal": false,
          "shootout": false
        }
      ],
      "liveStats": {
        "teams": [
          "BRA",
          "NOR"
        ],
        "rows": [
          {
            "name": "totalShots",
            "label": "射門",
            "values": {
              "BRA": "14",
              "NOR": "9"
            }
          },
          {
            "name": "shotsOnTarget",
            "label": "射正",
            "values": {
              "BRA": "4",
              "NOR": "5"
            }
          },
          {
            "name": "possessionPct",
            "label": "控球",
            "values": {
              "BRA": "33.6%",
              "NOR": "66.4%"
            }
          },
          {
            "name": "foulsCommitted",
            "label": "犯規",
            "values": {
              "BRA": "7",
              "NOR": "6"
            }
          },
          {
            "name": "yellowCards",
            "label": "黃牌",
            "values": {
              "BRA": "1",
              "NOR": "0"
            }
          },
          {
            "name": "redCards",
            "label": "紅牌",
            "values": {
              "BRA": "0",
              "NOR": "0"
            }
          },
          {
            "name": "wonCorners",
            "label": "角球",
            "values": {
              "BRA": "5",
              "NOR": "5"
            }
          },
          {
            "name": "offsides",
            "label": "越位",
            "values": {
              "BRA": "1",
              "NOR": "1"
            }
          },
          {
            "name": "saves",
            "label": "撲救",
            "values": {
              "BRA": "3",
              "NOR": "4"
            }
          }
        ],
        "sourceError": null
      },
      "cardCounts": {
        "BRA": {
          "yellow": 1,
          "red": 0
        },
        "NOR": {
          "yellow": 0,
          "red": 0
        }
      },
      "liveDataUpdatedAt": "2026-07-16T03:11:33+08:00",
      "taiwanSportsLottery": {
        "source": "Taiwan Sports Lottery",
        "status": "ok",
        "url": "https://www.sportslottery.com.tw/sportsbook/world-cup",
        "dataUrl": "https://blob3rd.sportslottery.com.tw/apidata/Pre/WC-Games.en.json",
        "updatedAt": "2026-07-06T00:09:49+08:00",
        "eventId": "3476440.1",
        "boardName": "Norway @ Brazil",
        "kickoff": "2026-07-06T04:00:00+08:00",
        "marketCount": 5,
        "markets": {
          "1x2": "Norway: 2.85x / Draw: 3.55x / Brazil: 1.50x",
          "total2.5": "Over 2.5: 1.40x / Under 2.5: 2.20x",
          "oddEven": "Odd: 1.68x / Even: 1.75x",
          "correctScoreShort": "1:2: 4.65x / 1:3: 6.25x / 2:2: 7.25x / 1:1: 7.25x / 2:1: 7.50x"
        }
      },
      "winner": "NOR",
      "resultSummary": "完賽 BRA 1 NOR 2，勝方/晉級方：NOR。總進球 3，大 2.5、小 3.5，BTTS Yes。90 分鐘勝負與讓球若涉及延長/PK，仍需以 Binance 結算規則核對。",
      "finishedAt": "2026-07-06T08:35:14+08:00"
    },
    "mex-eng": {
      "title": "墨西哥 vs 英格蘭",
      "kickoff": "2026-07-06T08:00:00+08:00",
      "lastScoreCheck": "2026-07-16T03:11:33+08:00",
      "espnStatus": "FT",
      "espnState": "post",
      "completed": true,
      "scoreDisplay": "MEX 2 ENG 3",
      "espnOdds": {},
      "status": "finished",
      "lastOddsUpdate": "2026-07-06T08:35:18+08:00",
      "lastPrematchOddsUpdate": "2026-07-06T08:35:18+08:00",
      "clock": "",
      "liveEvents": [
        {
          "time": "1'",
          "team": "ENG",
          "type": "黃牌",
          "rawType": "Yellow Card",
          "player": "Declan Rice",
          "scoringPlay": false,
          "yellowCard": true,
          "redCard": false,
          "penaltyKick": false,
          "ownGoal": false,
          "shootout": false
        },
        {
          "time": "36'",
          "team": "ENG",
          "type": "進球",
          "rawType": "Goal - Header",
          "player": "Jude Bellingham",
          "scoringPlay": true,
          "yellowCard": false,
          "redCard": false,
          "penaltyKick": false,
          "ownGoal": false,
          "shootout": false
        },
        {
          "time": "38'",
          "team": "ENG",
          "type": "進球",
          "rawType": "Goal",
          "player": "Jude Bellingham",
          "scoringPlay": true,
          "yellowCard": false,
          "redCard": false,
          "penaltyKick": false,
          "ownGoal": false,
          "shootout": false
        },
        {
          "time": "42'",
          "team": "MEX",
          "type": "進球",
          "rawType": "Goal",
          "player": "Julián Quiñones",
          "scoringPlay": true,
          "yellowCard": false,
          "redCard": false,
          "penaltyKick": false,
          "ownGoal": false,
          "shootout": false
        },
        {
          "time": "54'",
          "team": "ENG",
          "type": "紅牌",
          "rawType": "Red Card",
          "player": "Jarell Quansah",
          "scoringPlay": false,
          "yellowCard": false,
          "redCard": true,
          "penaltyKick": false,
          "ownGoal": false,
          "shootout": false
        },
        {
          "time": "60'",
          "team": "ENG",
          "type": "點球進球",
          "rawType": "Penalty - Scored",
          "player": "Harry Kane",
          "scoringPlay": true,
          "yellowCard": false,
          "redCard": false,
          "penaltyKick": true,
          "ownGoal": false,
          "shootout": false
        },
        {
          "time": "68'",
          "team": "ENG",
          "type": "黃牌",
          "rawType": "Yellow Card",
          "player": "Marc Guéhi",
          "scoringPlay": false,
          "yellowCard": true,
          "redCard": false,
          "penaltyKick": false,
          "ownGoal": false,
          "shootout": false
        },
        {
          "time": "69'",
          "team": "MEX",
          "type": "點球進球",
          "rawType": "Penalty - Scored",
          "player": "Raúl Jiménez",
          "scoringPlay": true,
          "yellowCard": false,
          "redCard": false,
          "penaltyKick": true,
          "ownGoal": false,
          "shootout": false
        },
        {
          "time": "71'",
          "team": "MEX",
          "type": "黃牌",
          "rawType": "Yellow Card",
          "player": "Jorge Sánchez",
          "scoringPlay": false,
          "yellowCard": true,
          "redCard": false,
          "penaltyKick": false,
          "ownGoal": false,
          "shootout": false
        },
        {
          "time": "72'",
          "team": "ENG",
          "type": "黃牌",
          "rawType": "Yellow Card",
          "player": "Nico O'Reilly",
          "scoringPlay": false,
          "yellowCard": true,
          "redCard": false,
          "penaltyKick": false,
          "ownGoal": false,
          "shootout": false
        },
        {
          "time": "90'+8'",
          "team": "MEX",
          "type": "黃牌",
          "rawType": "Yellow Card",
          "player": "Johan Vásquez",
          "scoringPlay": false,
          "yellowCard": true,
          "redCard": false,
          "penaltyKick": false,
          "ownGoal": false,
          "shootout": false
        },
        {
          "time": "90'+8'",
          "team": "ENG",
          "type": "黃牌",
          "rawType": "Yellow Card",
          "player": "Jordan Henderson",
          "scoringPlay": false,
          "yellowCard": true,
          "redCard": false,
          "penaltyKick": false,
          "ownGoal": false,
          "shootout": false
        }
      ],
      "liveStats": {
        "teams": [
          "MEX",
          "ENG"
        ],
        "rows": [
          {
            "name": "totalShots",
            "label": "射門",
            "values": {
              "MEX": "20",
              "ENG": "6"
            }
          },
          {
            "name": "shotsOnTarget",
            "label": "射正",
            "values": {
              "MEX": "5",
              "ENG": "5"
            }
          },
          {
            "name": "possessionPct",
            "label": "控球",
            "values": {
              "MEX": "66.9%",
              "ENG": "33.1%"
            }
          },
          {
            "name": "foulsCommitted",
            "label": "犯規",
            "values": {
              "MEX": "14",
              "ENG": "7"
            }
          },
          {
            "name": "yellowCards",
            "label": "黃牌",
            "values": {
              "MEX": "2",
              "ENG": "4"
            }
          },
          {
            "name": "redCards",
            "label": "紅牌",
            "values": {
              "MEX": "0",
              "ENG": "1"
            }
          },
          {
            "name": "wonCorners",
            "label": "角球",
            "values": {
              "MEX": "12",
              "ENG": "2"
            }
          },
          {
            "name": "offsides",
            "label": "越位",
            "values": {
              "MEX": "1",
              "ENG": "0"
            }
          },
          {
            "name": "saves",
            "label": "撲救",
            "values": {
              "MEX": "2",
              "ENG": "3"
            }
          }
        ],
        "sourceError": null
      },
      "cardCounts": {
        "MEX": {
          "yellow": 2,
          "red": 0
        },
        "ENG": {
          "yellow": 4,
          "red": 1
        }
      },
      "liveDataUpdatedAt": "2026-07-16T03:11:33+08:00",
      "taiwanSportsLottery": {
        "source": "Taiwan Sports Lottery",
        "status": "error",
        "url": "https://www.sportslottery.com.tw/sportsbook/world-cup",
        "dataUrl": "https://blob3rd.sportslottery.com.tw/apidata/Pre/WC-Games.en.json",
        "updatedAt": "2026-07-06T10:22:25+08:00",
        "error": "HTTP Error 403: Forbidden"
      },
      "winner": "ENG",
      "resultSummary": "完賽 MEX 2 ENG 3，勝方/晉級方：ENG。總進球 5，大 2.5、大 3.5，BTTS Yes。90 分鐘勝負與讓球若涉及延長/PK，仍需以 Binance 結算規則核對。",
      "finishedAt": "2026-07-06T11:59:44+08:00"
    },
    "por-esp": {
      "title": "葡萄牙 vs 西班牙",
      "kickoff": "2026-07-07T03:00:00+08:00",
      "lastScoreCheck": "2026-07-16T03:11:33+08:00",
      "espnStatus": "FT",
      "espnState": "post",
      "completed": true,
      "scoreDisplay": "POR 0 ESP 1",
      "espnOdds": {},
      "status": "finished",
      "lastOddsUpdate": "2026-07-06T08:35:18+08:00",
      "lastPrematchOddsUpdate": "2026-07-06T08:35:18+08:00",
      "clock": "",
      "liveEvents": [
        {
          "time": "89'",
          "team": "POR",
          "type": "黃牌",
          "rawType": "Yellow Card",
          "player": "Bernardo Silva",
          "scoringPlay": false,
          "yellowCard": true,
          "redCard": false,
          "penaltyKick": false,
          "ownGoal": false,
          "shootout": false
        },
        {
          "time": "90'+1'",
          "team": "ESP",
          "type": "進球",
          "rawType": "Goal",
          "player": "Mikel Merino",
          "scoringPlay": true,
          "yellowCard": false,
          "redCard": false,
          "penaltyKick": false,
          "ownGoal": false,
          "shootout": false
        },
        {
          "time": "90'+4'",
          "team": "POR",
          "type": "黃牌",
          "rawType": "Yellow Card",
          "player": "Renato Veiga",
          "scoringPlay": false,
          "yellowCard": true,
          "redCard": false,
          "penaltyKick": false,
          "ownGoal": false,
          "shootout": false
        },
        {
          "time": "90'+8'",
          "team": "ESP",
          "type": "黃牌",
          "rawType": "Yellow Card",
          "player": "Ferran Torres",
          "scoringPlay": false,
          "yellowCard": true,
          "redCard": false,
          "penaltyKick": false,
          "ownGoal": false,
          "shootout": false
        }
      ],
      "liveStats": {
        "teams": [
          "POR",
          "ESP"
        ],
        "rows": [
          {
            "name": "totalShots",
            "label": "射門",
            "values": {
              "POR": "10",
              "ESP": "15"
            }
          },
          {
            "name": "shotsOnTarget",
            "label": "射正",
            "values": {
              "POR": "2",
              "ESP": "6"
            }
          },
          {
            "name": "possessionPct",
            "label": "控球",
            "values": {
              "POR": "44.6%",
              "ESP": "55.4%"
            }
          },
          {
            "name": "foulsCommitted",
            "label": "犯規",
            "values": {
              "POR": "9",
              "ESP": "13"
            }
          },
          {
            "name": "yellowCards",
            "label": "黃牌",
            "values": {
              "POR": "2",
              "ESP": "1"
            }
          },
          {
            "name": "redCards",
            "label": "紅牌",
            "values": {
              "POR": "0",
              "ESP": "0"
            }
          },
          {
            "name": "wonCorners",
            "label": "角球",
            "values": {
              "POR": "3",
              "ESP": "7"
            }
          },
          {
            "name": "offsides",
            "label": "越位",
            "values": {
              "POR": "2",
              "ESP": "1"
            }
          },
          {
            "name": "saves",
            "label": "撲救",
            "values": {
              "POR": "5",
              "ESP": "2"
            }
          }
        ],
        "sourceError": null
      },
      "cardCounts": {
        "POR": {
          "yellow": 2,
          "red": 0
        },
        "ESP": {
          "yellow": 1,
          "red": 0
        }
      },
      "liveDataUpdatedAt": "2026-07-16T03:11:33+08:00",
      "taiwanSportsLottery": {
        "source": "Taiwan Sports Lottery",
        "status": "error",
        "url": "https://www.sportslottery.com.tw/sportsbook/world-cup",
        "dataUrl": "https://blob3rd.sportslottery.com.tw/apidata/Pre/WC-Games.en.json",
        "updatedAt": "2026-07-07T04:52:48+08:00",
        "error": "HTTP Error 403: Forbidden"
      },
      "winner": "ESP",
      "resultSummary": "完賽 POR 0 ESP 1，勝方/晉級方：ESP。總進球 1，小 2.5、小 3.5，BTTS No。90 分鐘勝負與讓球若涉及延長/PK，仍需以 Binance 結算規則核對。",
      "finishedAt": "2026-07-07T05:15:13+08:00"
    },
    "usa-bel": {
      "title": "美國 vs 比利時",
      "kickoff": "2026-07-07T08:00:00+08:00",
      "lastScoreCheck": "2026-07-16T03:11:33+08:00",
      "espnStatus": "FT",
      "espnState": "post",
      "completed": true,
      "scoreDisplay": "USA 1 BEL 4",
      "espnOdds": {},
      "status": "finished",
      "lastOddsUpdate": "2026-07-06T08:35:18+08:00",
      "lastPrematchOddsUpdate": "2026-07-06T08:35:18+08:00",
      "clock": "",
      "liveEvents": [
        {
          "time": "9'",
          "team": "BEL",
          "type": "進球",
          "rawType": "Goal",
          "player": "Charles De Ketelaere",
          "scoringPlay": true,
          "yellowCard": false,
          "redCard": false,
          "penaltyKick": false,
          "ownGoal": false,
          "shootout": false
        },
        {
          "time": "31'",
          "team": "USA",
          "type": "進球",
          "rawType": "Goal - Free-kick",
          "player": "Malik Tillman",
          "scoringPlay": true,
          "yellowCard": false,
          "redCard": false,
          "penaltyKick": false,
          "ownGoal": false,
          "shootout": false
        },
        {
          "time": "33'",
          "team": "BEL",
          "type": "進球",
          "rawType": "Goal - Header",
          "player": "Charles De Ketelaere",
          "scoringPlay": true,
          "yellowCard": false,
          "redCard": false,
          "penaltyKick": false,
          "ownGoal": false,
          "shootout": false
        },
        {
          "time": "35'",
          "team": "USA",
          "type": "黃牌",
          "rawType": "Yellow Card",
          "player": "Weston McKennie",
          "scoringPlay": false,
          "yellowCard": true,
          "redCard": false,
          "penaltyKick": false,
          "ownGoal": false,
          "shootout": false
        },
        {
          "time": "57'",
          "team": "BEL",
          "type": "進球",
          "rawType": "Goal",
          "player": "Hans Vanaken",
          "scoringPlay": true,
          "yellowCard": false,
          "redCard": false,
          "penaltyKick": false,
          "ownGoal": false,
          "shootout": false
        },
        {
          "time": "69'",
          "team": "USA",
          "type": "黃牌",
          "rawType": "Yellow Card",
          "player": "Malik Tillman",
          "scoringPlay": false,
          "yellowCard": true,
          "redCard": false,
          "penaltyKick": false,
          "ownGoal": false,
          "shootout": false
        },
        {
          "time": "90'+3'",
          "team": "BEL",
          "type": "進球",
          "rawType": "Goal",
          "player": "Romelu Lukaku",
          "scoringPlay": true,
          "yellowCard": false,
          "redCard": false,
          "penaltyKick": false,
          "ownGoal": false,
          "shootout": false
        }
      ],
      "liveStats": {
        "teams": [
          "USA",
          "BEL"
        ],
        "rows": [
          {
            "name": "totalShots",
            "label": "射門",
            "values": {
              "USA": "7",
              "BEL": "15"
            }
          },
          {
            "name": "shotsOnTarget",
            "label": "射正",
            "values": {
              "USA": "2",
              "BEL": "7"
            }
          },
          {
            "name": "possessionPct",
            "label": "控球",
            "values": {
              "USA": "55.9%",
              "BEL": "44.1%"
            }
          },
          {
            "name": "foulsCommitted",
            "label": "犯規",
            "values": {
              "USA": "11",
              "BEL": "9"
            }
          },
          {
            "name": "yellowCards",
            "label": "黃牌",
            "values": {
              "USA": "2",
              "BEL": "0"
            }
          },
          {
            "name": "redCards",
            "label": "紅牌",
            "values": {
              "USA": "0",
              "BEL": "0"
            }
          },
          {
            "name": "wonCorners",
            "label": "角球",
            "values": {
              "USA": "3",
              "BEL": "5"
            }
          },
          {
            "name": "offsides",
            "label": "越位",
            "values": {
              "USA": "0",
              "BEL": "1"
            }
          },
          {
            "name": "saves",
            "label": "撲救",
            "values": {
              "USA": "3",
              "BEL": "1"
            }
          }
        ],
        "sourceError": null
      },
      "cardCounts": {
        "USA": {
          "yellow": 2,
          "red": 0
        },
        "BEL": {
          "yellow": 0,
          "red": 0
        }
      },
      "liveDataUpdatedAt": "2026-07-16T03:11:33+08:00",
      "taiwanSportsLottery": {
        "source": "Taiwan Sports Lottery",
        "status": "error",
        "url": "https://www.sportslottery.com.tw/sportsbook/world-cup",
        "dataUrl": "https://blob3rd.sportslottery.com.tw/apidata/Pre/WC-Games.en.json",
        "updatedAt": "2026-07-07T08:07:39+08:00",
        "error": "HTTP Error 403: Forbidden"
      },
      "winner": "BEL",
      "resultSummary": "完賽 USA 1 BEL 4，勝方/晉級方：BEL。總進球 5，大 2.5、大 3.5，BTTS Yes。90 分鐘勝負與讓球若涉及延長/PK，仍需以 Binance 結算規則核對。",
      "finishedAt": "2026-07-07T10:10:15+08:00"
    },
    "arg-egy": {
      "title": "阿根廷 vs 埃及",
      "kickoff": "2026-07-08T00:00:00+08:00",
      "lastScoreCheck": "2026-07-16T03:11:33+08:00",
      "espnStatus": "FT",
      "espnState": "post",
      "completed": true,
      "scoreDisplay": "ARG 3 EGY 2",
      "espnOdds": {},
      "status": "finished",
      "lastOddsUpdate": "2026-07-04T23:37:39+08:00",
      "lastPrematchOddsUpdate": "2026-07-04T23:37:39+08:00",
      "clock": "",
      "liveEvents": [
        {
          "time": "15'",
          "team": "EGY",
          "type": "進球",
          "rawType": "Goal - Header",
          "player": "Yasser Ibrahim",
          "scoringPlay": true,
          "yellowCard": false,
          "redCard": false,
          "penaltyKick": false,
          "ownGoal": false,
          "shootout": false
        },
        {
          "time": "67'",
          "team": "EGY",
          "type": "進球",
          "rawType": "Goal",
          "player": "Mostafa Zico",
          "scoringPlay": true,
          "yellowCard": false,
          "redCard": false,
          "penaltyKick": false,
          "ownGoal": false,
          "shootout": false
        },
        {
          "time": "79'",
          "team": "ARG",
          "type": "進球",
          "rawType": "Goal - Header",
          "player": "Cristian Romero",
          "scoringPlay": true,
          "yellowCard": false,
          "redCard": false,
          "penaltyKick": false,
          "ownGoal": false,
          "shootout": false
        },
        {
          "time": "83'",
          "team": "ARG",
          "type": "進球",
          "rawType": "Goal",
          "player": "Lionel Messi",
          "scoringPlay": true,
          "yellowCard": false,
          "redCard": false,
          "penaltyKick": false,
          "ownGoal": false,
          "shootout": false
        },
        {
          "time": "90'+2'",
          "team": "ARG",
          "type": "進球",
          "rawType": "Goal - Header",
          "player": "Enzo Fernández",
          "scoringPlay": true,
          "yellowCard": false,
          "redCard": false,
          "penaltyKick": false,
          "ownGoal": false,
          "shootout": false
        },
        {
          "time": "90'+3'",
          "team": "EGY",
          "type": "黃牌",
          "rawType": "Yellow Card",
          "player": "Mostafa Shoubir",
          "scoringPlay": false,
          "yellowCard": true,
          "redCard": false,
          "penaltyKick": false,
          "ownGoal": false,
          "shootout": false
        },
        {
          "time": "90'+4'",
          "team": "EGY",
          "type": "黃牌",
          "rawType": "Yellow Card",
          "player": "Hamdy Fathy",
          "scoringPlay": false,
          "yellowCard": true,
          "redCard": false,
          "penaltyKick": false,
          "ownGoal": false,
          "shootout": false
        },
        {
          "time": "90'+8'",
          "team": "EGY",
          "type": "黃牌",
          "rawType": "Yellow Card",
          "player": "Marawan Attia",
          "scoringPlay": false,
          "yellowCard": true,
          "redCard": false,
          "penaltyKick": false,
          "ownGoal": false,
          "shootout": false
        },
        {
          "time": "90'+9'",
          "team": "EGY",
          "type": "黃牌",
          "rawType": "Yellow Card",
          "player": "",
          "scoringPlay": false,
          "yellowCard": true,
          "redCard": false,
          "penaltyKick": false,
          "ownGoal": false,
          "shootout": false
        },
        {
          "time": "90'+12'",
          "team": "EGY",
          "type": "黃牌",
          "rawType": "Yellow Card",
          "player": "Haissem Hassan",
          "scoringPlay": false,
          "yellowCard": true,
          "redCard": false,
          "penaltyKick": false,
          "ownGoal": false,
          "shootout": false
        }
      ],
      "liveStats": {
        "teams": [
          "ARG",
          "EGY"
        ],
        "rows": [
          {
            "name": "totalShots",
            "label": "射門",
            "values": {
              "ARG": "19",
              "EGY": "5"
            }
          },
          {
            "name": "shotsOnTarget",
            "label": "射正",
            "values": {
              "ARG": "7",
              "EGY": "2"
            }
          },
          {
            "name": "possessionPct",
            "label": "控球",
            "values": {
              "ARG": "63.6%",
              "EGY": "36.4%"
            }
          },
          {
            "name": "foulsCommitted",
            "label": "犯規",
            "values": {
              "ARG": "13",
              "EGY": "11"
            }
          },
          {
            "name": "yellowCards",
            "label": "黃牌",
            "values": {
              "ARG": "0",
              "EGY": "4"
            }
          },
          {
            "name": "redCards",
            "label": "紅牌",
            "values": {
              "ARG": "0",
              "EGY": "0"
            }
          },
          {
            "name": "wonCorners",
            "label": "角球",
            "values": {
              "ARG": "6",
              "EGY": "1"
            }
          },
          {
            "name": "offsides",
            "label": "越位",
            "values": {
              "ARG": "3",
              "EGY": "0"
            }
          },
          {
            "name": "saves",
            "label": "撲救",
            "values": {
              "ARG": "0",
              "EGY": "4"
            }
          }
        ],
        "sourceError": null
      },
      "cardCounts": {
        "ARG": {
          "yellow": 0,
          "red": 0
        },
        "EGY": {
          "yellow": 5,
          "red": 0
        }
      },
      "liveDataUpdatedAt": "2026-07-16T03:11:33+08:00",
      "taiwanSportsLottery": {
        "source": "Taiwan Sports Lottery",
        "status": "error",
        "url": "https://www.sportslottery.com.tw/sportsbook/world-cup",
        "dataUrl": "https://blob3rd.sportslottery.com.tw/apidata/Pre/WC-Games.en.json",
        "updatedAt": "2026-07-08T01:07:15+08:00",
        "error": "HTTP Error 403: Forbidden"
      },
      "winner": "ARG",
      "resultSummary": "完賽 ARG 3 EGY 2，勝方/晉級方：ARG。總進球 5，大 2.5、大 3.5，BTTS Yes。90 分鐘勝負與讓球若涉及延長/PK，仍需以 Binance 結算規則核對。",
      "finishedAt": "2026-07-08T02:29:39+08:00"
    },
    "sui-col": {
      "title": "瑞士 vs 哥倫比亞",
      "kickoff": "2026-07-08T04:00:00+08:00",
      "lastScoreCheck": "2026-07-16T03:11:33+08:00",
      "espnStatus": "FT-Pens",
      "espnState": "post",
      "completed": true,
      "scoreDisplay": "SUI 0 COL 0",
      "espnOdds": {},
      "status": "finished",
      "lastOddsUpdate": "2026-07-04T23:37:39+08:00",
      "lastPrematchOddsUpdate": "2026-07-04T23:37:39+08:00",
      "clock": "",
      "liveEvents": [
        {
          "time": "51'",
          "team": "SUI",
          "type": "黃牌",
          "rawType": "Yellow Card",
          "player": "Granit Xhaka",
          "scoringPlay": false,
          "yellowCard": true,
          "redCard": false,
          "penaltyKick": false,
          "ownGoal": false,
          "shootout": false
        },
        {
          "time": "59'",
          "team": "SUI",
          "type": "黃牌",
          "rawType": "Yellow Card",
          "player": "Denis Zakaria",
          "scoringPlay": false,
          "yellowCard": true,
          "redCard": false,
          "penaltyKick": false,
          "ownGoal": false,
          "shootout": false
        },
        {
          "time": "60'",
          "team": "COL",
          "type": "黃牌",
          "rawType": "Yellow Card",
          "player": "Luis Suárez",
          "scoringPlay": false,
          "yellowCard": true,
          "redCard": false,
          "penaltyKick": false,
          "ownGoal": false,
          "shootout": false
        },
        {
          "time": "95'",
          "team": "COL",
          "type": "黃牌",
          "rawType": "Yellow Card",
          "player": "Davinson Sánchez",
          "scoringPlay": false,
          "yellowCard": true,
          "redCard": false,
          "penaltyKick": false,
          "ownGoal": false,
          "shootout": false
        },
        {
          "time": "105'",
          "team": "SUI",
          "type": "黃牌",
          "rawType": "Yellow Card",
          "player": "Miro Muheim",
          "scoringPlay": false,
          "yellowCard": true,
          "redCard": false,
          "penaltyKick": false,
          "ownGoal": false,
          "shootout": false
        },
        {
          "time": "120'",
          "team": "COL",
          "type": "點球進球",
          "rawType": "Penalty - Scored",
          "player": "Juan Fernando Quintero",
          "scoringPlay": true,
          "yellowCard": false,
          "redCard": false,
          "penaltyKick": true,
          "ownGoal": false,
          "shootout": true
        },
        {
          "time": "120'",
          "team": "SUI",
          "type": "點球進球",
          "rawType": "Penalty - Scored",
          "player": "Granit Xhaka",
          "scoringPlay": true,
          "yellowCard": false,
          "redCard": false,
          "penaltyKick": true,
          "ownGoal": false,
          "shootout": true
        },
        {
          "time": "120'",
          "team": "SUI",
          "type": "點球進球",
          "rawType": "Penalty - Scored",
          "player": "Zeki Amdouni",
          "scoringPlay": true,
          "yellowCard": false,
          "redCard": false,
          "penaltyKick": true,
          "ownGoal": false,
          "shootout": true
        },
        {
          "time": "120'",
          "team": "COL",
          "type": "點球進球",
          "rawType": "Penalty - Scored",
          "player": "Jáminton Campaz",
          "scoringPlay": true,
          "yellowCard": false,
          "redCard": false,
          "penaltyKick": true,
          "ownGoal": false,
          "shootout": true
        },
        {
          "time": "120'",
          "team": "SUI",
          "type": "點球進球",
          "rawType": "Penalty - Scored",
          "player": "Cedric Itten",
          "scoringPlay": true,
          "yellowCard": false,
          "redCard": false,
          "penaltyKick": true,
          "ownGoal": false,
          "shootout": true
        },
        {
          "time": "120'",
          "team": "COL",
          "type": "點球進球",
          "rawType": "Penalty - Scored",
          "player": "Luis Díaz",
          "scoringPlay": true,
          "yellowCard": false,
          "redCard": false,
          "penaltyKick": true,
          "ownGoal": false,
          "shootout": true
        },
        {
          "time": "120'",
          "team": "SUI",
          "type": "點球進球",
          "rawType": "Penalty - Scored",
          "player": "Rubén Vargas",
          "scoringPlay": true,
          "yellowCard": false,
          "redCard": false,
          "penaltyKick": true,
          "ownGoal": false,
          "shootout": true
        }
      ],
      "liveStats": {
        "teams": [
          "SUI",
          "COL"
        ],
        "rows": [
          {
            "name": "totalShots",
            "label": "射門",
            "values": {
              "SUI": "7",
              "COL": "15"
            }
          },
          {
            "name": "shotsOnTarget",
            "label": "射正",
            "values": {
              "SUI": "2",
              "COL": "3"
            }
          },
          {
            "name": "possessionPct",
            "label": "控球",
            "values": {
              "SUI": "53.4%",
              "COL": "46.6%"
            }
          },
          {
            "name": "foulsCommitted",
            "label": "犯規",
            "values": {
              "SUI": "22",
              "COL": "21"
            }
          },
          {
            "name": "yellowCards",
            "label": "黃牌",
            "values": {
              "SUI": "3",
              "COL": "2"
            }
          },
          {
            "name": "redCards",
            "label": "紅牌",
            "values": {
              "SUI": "0",
              "COL": "0"
            }
          },
          {
            "name": "wonCorners",
            "label": "角球",
            "values": {
              "SUI": "3",
              "COL": "7"
            }
          },
          {
            "name": "offsides",
            "label": "越位",
            "values": {
              "SUI": "5",
              "COL": "4"
            }
          },
          {
            "name": "saves",
            "label": "撲救",
            "values": {
              "SUI": "3",
              "COL": "2"
            }
          }
        ],
        "sourceError": null
      },
      "cardCounts": {
        "SUI": {
          "yellow": 3,
          "red": 0
        },
        "COL": {
          "yellow": 2,
          "red": 0
        }
      },
      "liveDataUpdatedAt": "2026-07-16T03:11:33+08:00",
      "taiwanSportsLottery": {
        "source": "Taiwan Sports Lottery",
        "status": "error",
        "url": "https://www.sportslottery.com.tw/sportsbook/world-cup",
        "dataUrl": "https://blob3rd.sportslottery.com.tw/apidata/Pre/WC-Games.en.json",
        "updatedAt": "2026-07-08T06:01:49+08:00",
        "error": "HTTP Error 403: Forbidden"
      },
      "winner": "SUI",
      "resultSummary": "完賽 SUI 0 COL 0，勝方/晉級方：SUI。總進球 0，小 2.5、小 3.5，BTTS No。90 分鐘勝負與讓球若涉及延長/PK，仍需以 Binance 結算規則核對。",
      "finishedAt": "2026-07-08T07:04:24+08:00"
    }
  }
}